dtsnejedi/__init__.py
dtsnejedi/algorithms/__init__.py
dtsnejedi/algorithms/dtsne.py
dtsnejedi/algorithms/jedi.py
dtsnejedi/utils/__init__.py
dtsnejedi/utils/data_gen.py
dtsnejedi/utils/metrics.py
dtsnejedi/utils/utils.py
dtsnejedi-0.1.4.dist-info/METADATA
dtsnejedi-0.1.4.dist-info/WHEEL
dtsnejedi-0.1.4.dist-info/top_level.txt
dtsnejedi-0.1.4.dist-info/RECORD
