Metadata-Version: 2.1
Name: dtsnejedi
Version: 0.1.4
Author: Aleksandr Odnakov
Author-email: me@dnakov.ooo
Requires-Dist: matplotlib
Requires-Dist: numpy
Requires-Dist: scipy
Requires-Dist: tqdm
